alpa/__init__.py
alpa/api.py
alpa/create_state_parallel.py
alpa/data_loader.py
alpa/device_mesh.py
alpa/global_env.py
alpa/mesh_executable.py
alpa/mesh_profiling.py
alpa/monkey_patch.py
alpa/parallel_method.py
alpa/parallel_plan.py
alpa/serialization.py
alpa/test_install.py
alpa/testing.py
alpa/timer.py
alpa/util.py
alpa/collective/__init__.py
alpa/collective/collective.py
alpa/collective/const.py
alpa/collective/types.py
alpa/collective/util.py
alpa/collective/worker_nccl_util_cupy.py
alpa/collective/worker_nccl_util_xla.py
alpa/collective/collective_group/__init__.py
alpa/collective/collective_group/base_collective_group.py
alpa/collective/collective_group/cuda_stream.py
alpa/collective/collective_group/gloo_collective_group.py
alpa/collective/collective_group/gloo_util.py
alpa/collective/collective_group/nccl_collective_group.py
alpa/collective/collective_group/nccl_util.py
alpa/collective/collective_group/xla_nccl_collective_group.py
alpa/collective/collective_group/xla_nccl_util.py
alpa/model/__init__.py
alpa/model/bert_model.py
alpa/model/conformer.py
alpa/model/gpt_model.py
alpa/model/model_util.py
alpa/model/moe.py
alpa/model/wide_resnet.py
alpa/pipeline_parallel/__init__.py
alpa/pipeline_parallel/apply_grad.py
alpa/pipeline_parallel/compile_executable.py
alpa/pipeline_parallel/computation.py
alpa/pipeline_parallel/cross_mesh_resharding.py
alpa/pipeline_parallel/layer_construction.py
alpa/pipeline_parallel/layer_stats.py
alpa/pipeline_parallel/local_pipeline.py
alpa/pipeline_parallel/pipeshard_executable.py
alpa/pipeline_parallel/primitive_def.py
alpa/pipeline_parallel/resharding_tensor.py
alpa/pipeline_parallel/runtime_emitter.py
alpa/pipeline_parallel/schedules.py
alpa/pipeline_parallel/stage_construction.py
alpa/pipeline_parallel/stage_profiling.py
alpa/pipeline_parallel/xla_custom_call_marker/__init__.py
alpa/pipeline_parallel/xla_custom_call_marker/build/xla_custom_call_marker.cpython-39-x86_64-linux-gnu.so
alpa/shard_parallel/__init__.py
alpa-0.1.4.dist-info/LICENSE
alpa-0.1.4.dist-info/METADATA
alpa-0.1.4.dist-info/WHEEL
alpa-0.1.4.dist-info/top_level.txt
alpa-0.1.4.dist-info/RECORD
