Metadata-Version: 2.1
Name: alpa
Version: 0.1.4
Summary: Alpa automatically parallelizes large tensor computation graphs and runs them on a distributed cluster.
Home-page: https://github.com/alpa-projects/alpa
Author: Alpa team
Author-email: 
Keywords: alpa distributed parallel machine-learning model-parallelismgpt-3 deep-learning language-model python
Classifier: Programming Language :: Python :: 3
Classifier: Topic :: Scientific/Engineering :: Artificial Intelligence
Requires-Python: >=3.7
License-File: LICENSE
Requires-Dist: tqdm
Requires-Dist: ray[default]
Requires-Dist: jax (==0.3.5)
Requires-Dist: flax (==0.4.1)
Requires-Dist: pulp
Requires-Dist: tensorstore
Requires-Dist: numpy (==1.20)
Requires-Dist: numba
Provides-Extra: dev
Requires-Dist: cupy-cuda111 ; extra == 'dev'
Requires-Dist: yapf (==0.32.0) ; extra == 'dev'
Requires-Dist: pylint (==2.14.0) ; extra == 'dev'
Requires-Dist: cmake ; extra == 'dev'
Requires-Dist: pybind11 ; extra == 'dev'
Provides-Extra: doc
Requires-Dist: sphinx ; extra == 'doc'
Requires-Dist: sphinx-rtd-theme ; extra == 'doc'
Requires-Dist: sphinx-gallery ; extra == 'doc'
Requires-Dist: matplotlib ; extra == 'doc'
Requires-Dist: cupy-cuda111 ; extra == 'doc'
Requires-Dist: yapf (==0.32.0) ; extra == 'doc'
Requires-Dist: pylint (==2.14.0) ; extra == 'doc'
Requires-Dist: cmake ; extra == 'doc'
Requires-Dist: pybind11 ; extra == 'doc'
